uglypty/__init__.py
uglypty/__main__.py
uglypty/create_db.py
uglypty/creds_dlg.py
uglypty/creds_ui.py
uglypty/generate_key.py
uglypty/last_diff.html
uglypty/log_viewer2.py
uglypty/log_viewer_widget.py
uglypty/readme.py
uglypty/uglydiff2.py
uglypty/uglydiff_ui.py
uglypty/Library/__init__.py
uglypty/Library/collector_lib.py
uglypty/Library/creds_dlg.py
uglypty/Library/creds_ui.py
uglypty/Library/creds_widget.py
uglypty/Library/db.py
uglypty/Library/log_viewer2.py
uglypty/Library/log_viewer_widget.py
uglypty/Library/model2.py
uglypty/Library/models.py
uglypty/Library/parser_examples.py
uglypty/Library/plugins.py
uglypty/Library/qtssh_widget.py
uglypty/Library/sshschemahandler.py
uglypty/Library/sshshell.py
uglypty/Library/sshshell_depricated.py
uglypty/Library/sshshellreader.py
uglypty/Library/util.py
uglypty/Library/__pycache__/__init__.cpython-39.pyc
uglypty/Library/__pycache__/collector_lib.cpython-39.pyc
uglypty/Library/__pycache__/creds_dlg.cpython-39.pyc
uglypty/Library/__pycache__/creds_widget.cpython-39.pyc
uglypty/Library/__pycache__/db.cpython-39.pyc
uglypty/Library/__pycache__/models.cpython-39.pyc
uglypty/Library/__pycache__/parser_examples.cpython-39.pyc
uglypty/Library/__pycache__/plugins.cpython-39.pyc
uglypty/Library/__pycache__/qtssh_widget.cpython-39.pyc
uglypty/Library/__pycache__/sshschemahandler.cpython-39.pyc
uglypty/Library/__pycache__/sshshell.cpython-39.pyc
uglypty/Library/__pycache__/sshshellreader.cpython-39.pyc
uglypty/Library/__pycache__/util.cpython-39.pyc
uglypty/icons/ace.svg
uglypty/icons/cancel.svg
uglypty/icons/close.svg
uglypty/icons/close2.svg
uglypty/icons/code.svg
uglypty/icons/configmgmt.svg
uglypty/icons/credential_key.svg
uglypty/icons/credentials.svg
uglypty/icons/deviceinfo.svg
uglypty/icons/exit.png
uglypty/icons/exitapp.svg
uglypty/icons/file.png
uglypty/icons/file.svg
uglypty/icons/filecopy.svg
uglypty/icons/filenew.svg
uglypty/icons/folder.png
uglypty/icons/folder.svg
uglypty/icons/folder_open.png
uglypty-0.9.4.dist-info/METADATA
uglypty-0.9.4.dist-info/WHEEL
uglypty-0.9.4.dist-info/top_level.txt
uglypty-0.9.4.dist-info/RECORD
