Metadata-Version: 2.1
Name: uglypty
Version: 0.9.4
Summary: UglyPTY - A PyQt6-based SSH, Serial Console, Mapping and Automation Tooling.
Home-page: https://github.com/scottpeterman/UglyPTY
Author: Scott Peterman
Author-email: scottpeterman@gmail.com
License: GPLv3
Platform: UNKNOWN
Classifier: Programming Language :: Python :: 3.9
Classifier: License :: OSI Approved :: GNU General Public License v3 (GPLv3)
Classifier: Operating System :: OS Independent
Requires-Python: >=3.9
Requires-Dist: asttokens >=2.2.1
Requires-Dist: backcall >=0.2.0
Requires-Dist: bcrypt >=4.0.1
Requires-Dist: bs4 >=0.0.1
Requires-Dist: cached-property >=1.5.2
Requires-Dist: certifi >=2023.7.22
Requires-Dist: cffi >=1.15.1
Requires-Dist: charset-normalizer >=3.2.0
Requires-Dist: click >=8.1.3
Requires-Dist: colorama >=0.4.6
Requires-Dist: crayons >=0.4.0
Requires-Dist: cryptography >=41.0.1
Requires-Dist: darkdetect >=0.7.1
Requires-Dist: decorator >=5.1.1
Requires-Dist: diff-match-patch >=20230430
Requires-Dist: executing >=1.2.0
Requires-Dist: future >=0.18.3
Requires-Dist: greenlet >=2.0.2
Requires-Dist: idle >=1.0.4
Requires-Dist: idna >=3.4
Requires-Dist: hnmp ==0.5.1
Requires-Dist: pyasn1 ==0.4.8
Requires-Dist: matplotlib >=3.8.2
Requires-Dist: igraph >=0.10.6
Requires-Dist: inflection >=0.5.1
Requires-Dist: jedi >=0.19.0
Requires-Dist: Jinja2 >=3.1.2
Requires-Dist: jmespath >=1.0.1
Requires-Dist: ldap3 >=2.9.1
Requires-Dist: MarkupSafe >=2.1.3
Requires-Dist: matplotlib-inline >=0.1.6
Requires-Dist: mypy-extensions >=1.0.0
Requires-Dist: netmiko >=3.3.3
Requires-Dist: numpy >=1.25.2
Requires-Dist: n2g >=0.3.3
Requires-Dist: pandas >=2.0.3
Requires-Dist: pandasql >=0.7.3
Requires-Dist: paramiko >=3.2.0
Requires-Dist: parso >=0.8.3
Requires-Dist: pickleshare >=0.7.5
Requires-Dist: prompt-toolkit >=3.0.39
Requires-Dist: pure-eval >=0.2.2
Requires-Dist: pycparser >=2.21
Requires-Dist: pycryptodome >=3.18.0
Requires-Dist: Pygments >=2.16.1
Requires-Dist: pyftpdlib >=1.5.9
Requires-Dist: PyNaCl >=1.5.0
Requires-Dist: PyQt6 >=6.5.1
Requires-Dist: PyQt6-Qt6 >=6.5.1
Requires-Dist: PyQt6-sip >=13.5.1
Requires-Dist: PyQt6-WebEngine >=6.5.0
Requires-Dist: PyQt6-WebEngine-Qt6 >=6.5.1
Requires-Dist: pyqtdarktheme >=2.1.0
Requires-Dist: pyserial >=3.5
Requires-Dist: python-dateutil >=2.8.2
Requires-Dist: python-igraph >=0.10.6
Requires-Dist: pytz >=2023.3
Requires-Dist: pynetbox >=7.2.0
Requires-Dist: PyYAML >=6.0.1
Requires-Dist: qt-material >=2.14
Requires-Dist: requests >=2.31.0
Requires-Dist: scp >=0.14.5
Requires-Dist: six >=1.16.0
Requires-Dist: SQLAlchemy >=2.0.20
Requires-Dist: sqlalchemy-orm >=1.2.10
Requires-Dist: SQLAlchemy-serializer >=1.4.1
Requires-Dist: stack-data >=0.6.2
Requires-Dist: svgwrite >=1.4.3
Requires-Dist: textfsm >=1.1.3
Requires-Dist: texttable >=1.6.7
Requires-Dist: tomli >=2.0.1
Requires-Dist: tqdm >=4.66.1
Requires-Dist: tftpy >=0.8.2
Requires-Dist: ttp >=0.9.5
Requires-Dist: traitlets >=5.9.0
Requires-Dist: typing-inspect >=0.9.0
Requires-Dist: typing-extensions >=4.7.1
Requires-Dist: tzdata >=2023.3
Requires-Dist: urllib3 >=2.0.4
Requires-Dist: wcwidth >=0.2.6
